mailreceiver_webthing/__init__.py
mailreceiver_webthing/app.py
mailreceiver_webthing/mail_receiver_webthing.py
mailreceiver_webthing/mailserver.py
mailreceiver_webthing-0.1.8.dist-info/LICENSE
mailreceiver_webthing-0.1.8.dist-info/METADATA
mailreceiver_webthing-0.1.8.dist-info/WHEEL
mailreceiver_webthing-0.1.8.dist-info/entry_points.txt
mailreceiver_webthing-0.1.8.dist-info/top_level.txt
mailreceiver_webthing-0.1.8.dist-info/RECORD
