Metadata-Version: 2.1
Name: mailreceiver-webthing
Version: 0.1.8
Summary: A web connected mail receiver
Home-page: https://github.com/grro/mailreceiver_webthing
Author: Gregor Roth
Author-email: gregor.roth@web.de
License: MIT
Keywords: webthings,home automation,mail,server
Platform: UNKNOWN
Classifier: Programming Language :: Python :: 3
Classifier: License :: OSI Approved :: Apache Software License
Classifier: Operating System :: OS Independent
Classifier: Development Status :: 3 - Alpha
Requires-Dist: webthing (==0.15.0)
